{"id":"FilterableList_2318DE10_CDE5_484F_BA44_2A0437726871","snapshot":{"FilterableList_2318DE10_CDE5_484F_BA44_2A0437726871":{"rev":129983,"props":{"attributeConnections":{"value":[{"__ref__":true,"id":"8806ADDE-2859-4798-BF4A-D4B65E36161C","rev":0}]},"name":{"value":"autocomplete list"},"isComponent":{"value":true},"position":{"value":"__lv_expr__:{pt}:lively.graphics/geometry-2d.js:pt(401.10546875,753.16796875)"},"extent":{"value":"__lv_expr__:{pt}:lively.graphics/geometry-2d.js:pt(400,360)"},"submorphs":{"value":[{"__ref__":true,"id":"InputLine_56336B4A_FB8B_4CC2_B7B8_437FDC6D6D45","rev":129869},{"__ref__":true,"id":"Morph_42C6FA8F_566D_43EB_B2B4_B0B3AC7CA1DB","rev":129879},{"__ref__":true,"id":"ProtoList_7A6CA951_3927_418F_8083_80E96705D8B2","rev":129976}]},"styleClasses":{"value":["FilterableList","Morph","morph"]},"borderWidth":{"key":"borderWidth","verbatim":true,"value":{"top":0,"right":0,"bottom":0,"left":0}},"filterFunction":{},"fuzzySortFunction":{},"fuzzyFilterFunction":{},"selectedAction":{"value":"default"}},"lively.serializer-class-info":{"className":"FilterableList","module":{"package":{"name":"lively.components","version":"0.1.0"},"pathInPackage":"list.js"}}},"8806ADDE-2859-4798-BF4A-D4B65E36161C":{"rev":0,"props":{"_rev":{"value":0},"doNotSerialize":{"value":["isActive","converter","updater","varMapping"]},"sourceObj":{"value":{"__ref__":true,"id":"FilterableList_2318DE10_CDE5_484F_BA44_2A0437726871","rev":129983}},"sourceAttrName":{"value":"extent"},"targetObj":{"value":{"__ref__":true,"id":"FilterableList_2318DE10_CDE5_484F_BA44_2A0437726871","rev":129983}},"targetMethodName":{"value":"relayout"},"garbageCollect":{"value":false},"signalOnAssignment":{"value":true}},"lively.serializer-class-info":{"className":"AttributeConnection","module":{"package":{"name":"lively.bindings","version":"0.1.2"},"pathInPackage":"index.js"}}},"InputLine_56336B4A_FB8B_4CC2_B7B8_437FDC6D6D45":{"rev":129869,"props":{"attributeConnections":{"value":[{"__ref__":true,"id":"A1CEC6A6-1072-4146-BFC3-43B84DE30F09","rev":0},{"__ref__":true,"id":"A84E700B-0163-4EB5-8B07-D891E853BE2B","rev":0},{"__ref__":true,"id":"A6855F24-FBAB-4D7C-A289-2DC619328956","rev":0}]},"name":{"value":"input"},"extent":{"value":"__lv_expr__:{pt}:lively.graphics/geometry-2d.js:pt(400,5)"},"fill":{"value":"__lv_expr__:{Color}:lively.graphics/color.js:Color.rgba(255,255,255,0)"},"styleClasses":{"value":["InputLine","Text","Morph","morph"]},"fixedHeight":{"value":false},"padding":{"value":"__lv_expr__:{rect}:lively.graphics/geometry-2d.js:rect(0,3,0,-1)"},"fontFamily":{"value":"\"IBM Plex Mono\""},"anchors":{"value":[{"__ref__":true,"id":"475B4879-F328-494C-BE59-33758832AF8E","rev":0}]},"savedMarks":{"value":[{"__ref__":true,"id":"475B4879-F328-494C-BE59-33758832AF8E","rev":0}]},"selections":{"key":"selections","verbatim":true,"value":[{"start":{"row":0,"column":0},"end":{"row":0,"column":0}}]},"textAndAttributes":{"key":"textAndAttributes","value":["",null]}},"lively.serializer-class-info":{"className":"InputLine","module":{"package":{"name":"lively.morphic","version":"0.1.2"},"pathInPackage":"text/input-line.js"}},"cachedLineBounds":[[0,[1,7.203,15]]]},"A1CEC6A6-1072-4146-BFC3-43B84DE30F09":{"rev":0,"props":{"_rev":{"value":0},"doNotSerialize":{"value":["isActive","converter","updater","varMapping"]},"sourceObj":{"value":{"__ref__":true,"id":"InputLine_56336B4A_FB8B_4CC2_B7B8_437FDC6D6D45","rev":129869}},"sourceAttrName":{"value":"textChange"},"targetObj":{"value":{"__ref__":true,"id":"InputLine_56336B4A_FB8B_4CC2_B7B8_437FDC6D6D45","rev":129869}},"targetMethodName":{"value":"onInputChanged"},"garbageCollect":{"value":false},"signalOnAssignment":{"value":true}},"lively.serializer-class-info":{"className":"AttributeConnection","module":{"package":{"name":"lively.bindings","version":"0.1.2"},"pathInPackage":"index.js"}}},"A84E700B-0163-4EB5-8B07-D891E853BE2B":{"rev":0,"props":{"_rev":{"value":0},"doNotSerialize":{"value":["isActive","converter","updater","varMapping"]},"sourceObj":{"value":{"__ref__":true,"id":"InputLine_56336B4A_FB8B_4CC2_B7B8_437FDC6D6D45","rev":129869}},"sourceAttrName":{"value":"selectionChange"},"targetObj":{"value":{"__ref__":true,"id":"InputLine_56336B4A_FB8B_4CC2_B7B8_437FDC6D6D45","rev":129869}},"targetMethodName":{"value":"fixCursor"},"garbageCollect":{"value":false},"signalOnAssignment":{"value":true}},"lively.serializer-class-info":{"className":"AttributeConnection","module":{"package":{"name":"lively.bindings","version":"0.1.2"},"pathInPackage":"index.js"}}},"A6855F24-FBAB-4D7C-A289-2DC619328956":{"rev":0,"props":{"_rev":{"value":0},"doNotSerialize":{"value":["isActive","converter","updater","varMapping"]},"sourceObj":{"value":{"__ref__":true,"id":"InputLine_56336B4A_FB8B_4CC2_B7B8_437FDC6D6D45","rev":129869}},"sourceAttrName":{"value":"inputChanged"},"targetObj":{"value":{"__ref__":true,"id":"FilterableList_2318DE10_CDE5_484F_BA44_2A0437726871","rev":129983}},"targetMethodName":{"value":"updateFilter"},"garbageCollect":{"value":false},"signalOnAssignment":{"value":true}},"lively.serializer-class-info":{"className":"AttributeConnection","module":{"package":{"name":"lively.bindings","version":"0.1.2"},"pathInPackage":"index.js"}}},"475B4879-F328-494C-BE59-33758832AF8E":{"rev":0,"props":{"_rev":{"value":0},"id":{"value":null},"position":{"value":{"__ref__":true,"id":"E8E92079-EF55-4B9A-933E-137FFD6CF4B0","rev":0}},"insertBehavior":{"value":"move"}},"lively.serializer-class-info":{"className":"Anchor","module":{"package":{"name":"lively.morphic","version":"0.1.2"},"pathInPackage":"text/anchors.js"}}},"E8E92079-EF55-4B9A-933E-137FFD6CF4B0":{"rev":0,"props":{"_rev":{"value":0},"row":{"value":0},"column":{"value":0}}},"Morph_42C6FA8F_566D_43EB_B2B4_B0B3AC7CA1DB":{"rev":129879,"props":{"name":{"value":"padding"},"position":{"value":"__lv_expr__:{pt}:lively.graphics/geometry-2d.js:pt(0,21)"},"extent":{"value":"__lv_expr__:{pt}:lively.graphics/geometry-2d.js:pt(10,0)"},"fill":{"value":"__lv_expr__:{Color}:lively.graphics/color.js:Color.rgba(0,0,0,0)"},"styleClasses":{"value":["Morph","morph"]}},"lively.serializer-class-info":{"className":"Morph","module":{"package":{"name":"lively.morphic","version":"0.1.2"},"pathInPackage":"morph.js"}}},"ProtoList_7A6CA951_3927_418F_8083_80E96705D8B2":{"rev":129976,"props":{"attributeConnections":{"value":[{"__ref__":true,"id":"0147A96B-0AF2-420F-85CD-B964C52E4E02","rev":0},{"__ref__":true,"id":"0E88EBA9-EFAE-4D39-983A-7BEA73933248","rev":0}]},"name":{"value":"list"},"dropShadow":{"value":"__lv_expr__:{ShadowObject}:lively.morphic:{Color}:lively.graphics/color.js:new ShadowObject({distance:15,rotation:45,color:Color.rgba(0,0,0,0.35),inset:false,blur:52,spread:0,fast:true})"},"position":{"value":"__lv_expr__:{pt}:lively.graphics/geometry-2d.js:pt(0,21)"},"extent":{"value":"__lv_expr__:{pt}:lively.graphics/geometry-2d.js:pt(400,339)"},"fill":{"value":"__lv_expr__:{Color}:lively.graphics/color.js:Color.rgba(255,255,255,0.9)"},"submorphs":{"value":[{"__ref__":true,"id":"ListScroller_BFF142ED_5737_474B_9157_F1DD5DA6402B","rev":129977},{"__ref__":true,"id":"Morph_241FC898_0AB1_45E6_9535_B4DF7B526E0B","rev":129972}]},"clipMode":{"value":"auto"},"styleClasses":{"value":["ProtoList","List","Morph","default"]},"borderRadius":{"key":"borderRadius","verbatim":true,"value":{"top":3,"right":3,"bottom":3,"left":3}},"borderColor":{"key":"borderColor","verbatim":true,"value":{"top":[0.5843137254901961,0.6470588235294118,0.6509803921568628,1],"right":[0.5843137254901961,0.6470588235294118,0.6509803921568628,1],"bottom":[0.5843137254901961,0.6470588235294118,0.6509803921568628,1],"left":[0.5843137254901961,0.6470588235294118,0.6509803921568628,1]}},"fontFamily":{"value":"IBM Plex Mono"},"padding":{"value":"__lv_expr__:{rect}:lively.graphics/geometry-2d.js:rect(0,0,0,0)"},"itemPadding":{"value":"__lv_expr__:{rect}:lively.graphics/geometry-2d.js:rect(3,2,7,-1)"},"selectedIndex":{},"selectedIndexes":{"value":[]},"selections":{"value":[]},"manualItemHeight":{"value":true},"itemHeight":{"value":18}},"lively.serializer-class-info":{"className":"ProtoList","module":{"package":{"name":"ProtoList","version":"0.1.1-0"},"pathInPackage":"index.js"}}},"0147A96B-0AF2-420F-85CD-B964C52E4E02":{"rev":0,"props":{"_rev":{"value":0},"doNotSerialize":{"value":["isActive","converter","updater","varMapping"]},"sourceObj":{"value":{"__ref__":true,"id":"ProtoList_7A6CA951_3927_418F_8083_80E96705D8B2","rev":129976}},"sourceAttrName":{"value":"selection"},"targetObj":{"value":{"__ref__":true,"id":"FilterableList_2318DE10_CDE5_484F_BA44_2A0437726871","rev":129983}},"targetMethodName":{"value":"selectionChanged"},"garbageCollect":{"value":false},"signalOnAssignment":{"value":false}},"lively.serializer-class-info":{"className":"AttributeConnection","module":{"package":{"name":"lively.bindings","version":"0.1.2"},"pathInPackage":"index.js"}}},"0E88EBA9-EFAE-4D39-983A-7BEA73933248":{"rev":0,"props":{"_rev":{"value":0},"doNotSerialize":{"value":["isActive","converter","updater","varMapping"]},"sourceObj":{"value":{"__ref__":true,"id":"ProtoList_7A6CA951_3927_418F_8083_80E96705D8B2","rev":129976}},"sourceAttrName":{"value":"onItemMorphDoubleClicked"},"targetObj":{"value":{"__ref__":true,"id":"FilterableList_2318DE10_CDE5_484F_BA44_2A0437726871","rev":129983}},"targetMethodName":{"value":"acceptInput"},"garbageCollect":{"value":false},"signalOnAssignment":{"value":true}},"lively.serializer-class-info":{"className":"AttributeConnection","module":{"package":{"name":"lively.bindings","version":"0.1.2"},"pathInPackage":"index.js"}}},"ListScroller_BFF142ED_5737_474B_9157_F1DD5DA6402B":{"rev":129977,"props":{"acceptsDrops":{"value":false},"halosEnabled":{"value":false},"extent":{"value":"__lv_expr__:{pt}:lively.graphics/geometry-2d.js:pt(400,339)"},"visible":{"value":false},"submorphs":{"value":[{"__ref__":true,"id":"Morph_E7A1DC89_E20C_4979_9E01_6A31A894D514","rev":129958}]},"styleClasses":{"value":["ListScroller","Morph","morph"]}},"lively.serializer-class-info":{"className":"ListScroller","module":{"package":{"name":"lively.components","version":"0.1.0"},"pathInPackage":"list.js"}}},"Morph_E7A1DC89_E20C_4979_9E01_6A31A894D514":{"rev":129958,"props":{"name":{"value":"scrollbar"},"extent":{"value":"__lv_expr__:{pt}:lively.graphics/geometry-2d.js:pt(1,339)"},"fill":{"value":"__lv_expr__:{Color}:lively.graphics/color.js:Color.rgba(0,0,0,0)"},"styleClasses":{"value":["Morph","morph"]}},"lively.serializer-class-info":{"className":"Morph","module":{"package":{"name":"lively.morphic","version":"0.1.2"},"pathInPackage":"morph.js"}}},"Morph_241FC898_0AB1_45E6_9535_B4DF7B526E0B":{"rev":129972,"props":{"name":{"value":"listItemContainer"},"acceptsDrops":{"value":false},"halosEnabled":{"value":false},"reactsToPointer":{"value":false},"extent":{"value":"__lv_expr__:{pt}:lively.graphics/geometry-2d.js:pt(400,339)"},"fill":{"value":"__lv_expr__:{Color}:lively.graphics/color.js:Color.rgba(0,0,0,0)"},"styleClasses":{"value":["Morph","morph"]}},"lively.serializer-class-info":{"className":"Morph","module":{"package":{"name":"lively.morphic","version":"0.1.2"},"pathInPackage":"morph.js"}}}},"requiredVersion":">=0.1"}